protoc_gen_openapiv2/__init__.py
protoc_gen_openapiv2/options/__init__.py
protoc_gen_openapiv2/options/annotations_pb2.py
protoc_gen_openapiv2/options/openapiv2_pb2.py
grpc_gateway_protoc_gen_openapiv2-0.1.0.dist-info/LICENSE
grpc_gateway_protoc_gen_openapiv2-0.1.0.dist-info/METADATA
grpc_gateway_protoc_gen_openapiv2-0.1.0.dist-info/WHEEL
grpc_gateway_protoc_gen_openapiv2-0.1.0.dist-info/top_level.txt
grpc_gateway_protoc_gen_openapiv2-0.1.0.dist-info/RECORD
