Metadata-Version: 2.1
Name: grpc-gateway-protoc-gen-openapiv2
Version: 0.1.0
Summary: Provides the missing pieces for gRPC Gateway.
Home-page: https://github.com/hack-edu/py_protoc_gen_openapiv2
Author: HackEDU
Author-email: noah@hackedu.io
License: UNKNOWN
Project-URL: Bug Tracker, https://github.com/hack-edu/py_protoc_gen_openapiv2/issues
Platform: UNKNOWN
Classifier: Programming Language :: Python :: 3
Classifier: License :: OSI Approved :: BSD License
Classifier: Operating System :: OS Independent
Requires-Python: >=3.6
